vbox_api/__init__.py
vbox_api/constants.py
vbox_api/helpers.py
vbox_api/mixins.py
vbox_api/utils.py
vbox_api/api/__init__.py
vbox_api/api/context.py
vbox_api/api/core.py
vbox_api/api/handle.py
vbox_api/api/pool.py
vbox_api/cli/__init__.py
vbox_api/cli/__main__.py
vbox_api/cli/args.py
vbox_api/http/__init__.py
vbox_api/http/__main__.py
vbox_api/http/app.py
vbox_api/http/config.py
vbox_api/http/constants.py
vbox_api/http/gui.py
vbox_api/http/session.py
vbox_api/http/utils.py
vbox_api/http/static/favicon.png
vbox_api/http/static/css/bootstrap.min.css
vbox_api/http/static/images/logo.svg
vbox_api/http/static/js/bootstrap.bundle.min.js
vbox_api/http/templates/dashboard.html
vbox_api/http/templates/error.html
vbox_api/http/templates/events.html
vbox_api/http/templates/layout.html
vbox_api/http/templates/login.html
vbox_api/http/templates/machine/create.html
vbox_api/http/templates/machine/edit.html
vbox_api/http/templates/machine/logs.html
vbox_api/http/templates/machine/medium.html
vbox_api/http/templates/machine/overview.html
vbox_api/http/templates/machine/view.html
vbox_api/http/templates/medium/create.html
vbox_api/http/templates/medium/overview.html
vbox_api/http/views/__init__.py
vbox_api/http/views/machine.py
vbox_api/http/views/medium.py
vbox_api/interface/__init__.py
vbox_api/interface/base.py
vbox_api/interface/soap.py
vbox_api/models/__init__.py
vbox_api/models/audio.py
vbox_api/models/base.py
vbox_api/models/event.py
vbox_api/models/machine.py
vbox_api/models/medium.py
vbox_api/models/network.py
vbox_api/models/platform.py
vbox_api/models/progress.py
vbox_api/models/session.py
vbox_api/models/unattended.py
vbox_api/models/virtualbox.py
vbox_api/models/vrde.py
vbox_api_soap-2.1.2.dist-info/licenses/LICENSE
vbox_api_soap-2.1.2.dist-info/METADATA
vbox_api_soap-2.1.2.dist-info/WHEEL
vbox_api_soap-2.1.2.dist-info/entry_points.txt
vbox_api_soap-2.1.2.dist-info/top_level.txt
vbox_api_soap-2.1.2.dist-info/RECORD
