Metadata-Version: 2.4
Name: vbox-api-soap
Version: 2.1.2
Summary: Python bindings to the VirtualBox SOAP API.
Author: Zack Didcott
Maintainer: Zack Didcott
License-Expression: MIT
Project-URL: Homepage, https://github.com/Zedeldi/vbox-api
Project-URL: Repository, https://github.com/Zedeldi/vbox-api.git
Project-URL: Issues, https://github.com/Zedeldi/vbox-api/issues
Keywords: virtualbox,api,soap,zeep,flask
Classifier: Programming Language :: Python :: 3
Classifier: Operating System :: OS Independent
Requires-Python: >=3.10
License-File: LICENSE
Requires-Dist: Flask
Requires-Dist: pillow
Requires-Dist: zeep
Requires-Dist: psutil
Requires-Dist: websockify
Provides-Extra: tests
Requires-Dist: pytest; extra == "tests"
Provides-Extra: gui
Requires-Dist: flaskwebgui; extra == "gui"
Dynamic: license-file
